delphifmx/__init__.py
delphifmx/__version__.py
delphifmx/darwin_arm.py
delphifmx/Android/libDelphiFMX.so
delphifmx/Android64/libDelphiFMX.so
delphifmx/Linux64/libDelphiFMX.so
delphifmx/OSX64/libDelphiFMX.dylib
delphifmx/OSXARM64/libDelphiFMX.dylib
delphifmx/Win32/DelphiFMX.pyd
delphifmx/Win64/DelphiFMX.pyd
delphifmx/doc/docs.xml
delphifmx-1.1.0.dist-info/METADATA
delphifmx-1.1.0.dist-info/WHEEL
delphifmx-1.1.0.dist-info/top_level.txt
delphifmx-1.1.0.dist-info/RECORD
