Metadata-Version: 2.1
Name: delphifmx
Version: 1.1.0
Summary: Delphi FMX for Python
Home-page: https://github.com/Embarcadero/DelphiFMX4Python
Author: Lucas Belo, Jim McKeeth
Author-email: lucas.belo@live.com
License: BSD
Project-URL: Documentation, https://embarcadero.github.io/DelphiFMX4Python
Project-URL: Source, https://github.com/Embarcadero/DelphiFMX4Python
Project-URL: Tracker, https://github.com/Embarcadero/DelphiFMX4Python/issues
Classifier: Intended Audience :: Developers
Classifier: Topic :: Software Development
Classifier: License :: Other/Proprietary License
Classifier: Programming Language :: Python
Classifier: Programming Language :: Python :: 3
Classifier: Programming Language :: Python :: 3.6
Classifier: Programming Language :: Python :: 3.7
Classifier: Programming Language :: Python :: 3.8
Classifier: Programming Language :: Python :: 3.9
Classifier: Programming Language :: Python :: 3.10
Classifier: Programming Language :: Python :: 3.11
Classifier: Programming Language :: Python :: 3 :: Only
Classifier: Operating System :: Microsoft :: Windows
Classifier: Operating System :: POSIX
Classifier: Operating System :: Unix
Classifier: Operating System :: MacOS
Classifier: Operating System :: Android
Requires-Python: >=3
